guang/__init__.py
guang/guang.py
guang/utils.py
guang/version_config.yaml
guang/DL/__init__.py
guang/DL/Model/__init__.py
guang/DL/Model/cae.py
guang/DL/Model/dae.py
guang/ML/__init__.py
guang/ML/pca.py
guang/Utils/__init__.py
guang/Utils/bar.py
guang/Utils/date.py
guang/Utils/date_data
guang/Utils/distance.py
guang/Utils/google.py
guang/Utils/implot.py
guang/Utils/jupyter.py
guang/Utils/load_data.py
guang/Utils/mathFunc.py
guang/Utils/parse.py
guang/Utils/plot.py
guang/Utils/plotly.py
guang/Utils/show_tensorboard.py
guang/Utils/similarity.py
guang/Utils/symbols.py
guang/Utils/time.py
guang/Utils/toolsFunc.py
guang/Utils/trans.py
guang/Utils/wordProcessing.py
guang/Utils/animation/__init__.py
guang/Utils/animation/animation.py
guang/Utils/animation/drawer.py
guang/Utils/animation/slider.py
guang/Utils/animation/utils.py
guang/Voice/__init__.py
guang/Voice/convert.py
guang/Voice/music.py
guang/Voice/pinyin_to_phone.txt
guang/Voice/reduce.py
guang/Voice/tts.py
guang/Voice/txt2phone.py
guang/Voice/txt2pinyin.py
guang/app/__init__.py
guang/app/anim_demo.py
guang/app/compose/__init__.py
guang/app/compose/animation.py
guang/app/compose/slider.py
guang/app/lorenz/__init__.py
guang/cv/MajorTone.py
guang/cv/__init__.py
guang/cv/detect.py
guang/cv/imshow.py
guang/cv/loveFigure.py
guang/cv/makeSplineStroke.py
guang/cv/render.py
guang/cv/utils.py
guang/cv/video.py
guang/cv/vision.py
guang/cv/xkcd.py
guang/cv/xkcd_ffmpeg_have_bug_now.py
guang/cv/imageDeformation/__init__.py
guang/cv/imageDeformation/deformation_example.py
guang/cv/imageDeformation/gryds/__init__.py
guang/cv/imageDeformation/gryds/config.py
guang/cv/imageDeformation/gryds/utils.py
guang/cv/imageDeformation/gryds/interpolators/__init__.py
guang/cv/imageDeformation/gryds/interpolators/base.py
guang/cv/imageDeformation/gryds/interpolators/bspline.py
guang/cv/imageDeformation/gryds/interpolators/color.py
guang/cv/imageDeformation/gryds/interpolators/cuda.py
guang/cv/imageDeformation/gryds/interpolators/grid.py
guang-0.0.8.1.6.dist-info/LICENSE
guang-0.0.8.1.6.dist-info/METADATA
guang-0.0.8.1.6.dist-info/WHEEL
guang-0.0.8.1.6.dist-info/entry_points.txt
guang-0.0.8.1.6.dist-info/top_level.txt
guang-0.0.8.1.6.dist-info/RECORD
