Metadata-Version: 2.1
Name: guang
Version: 0.0.8.1.6
Summary: ML/DL tools function library
Home-page: https://github.com/beidongjiedeguang/guang
Author: K.y
Author-email: beidongjiedeguang@gmail.com
License: GPL-v3
Keywords: Deep Learning,Machine Learning,Neural Networks,Natural Language Processing,Computer Vision
Platform: UNKNOWN
Classifier: Operating System :: OS Independent
Classifier: Intended Audience :: Developers
Classifier: Intended Audience :: Science/Research
Classifier: Topic :: Scientific/Engineering :: Artificial Intelligence
Classifier: Programming Language :: Python :: 3
Classifier: Programming Language :: Python :: 3.5
Classifier: Programming Language :: Python :: 3.6
Classifier: Programming Language :: Python :: 3.7
Requires-Dist: gdown (>=3.11)
Requires-Dist: fire
Requires-Dist: pyyaml
Requires-Dist: yapf
Requires-Dist: wget
Requires-Dist: pendulum
Requires-Dist: pyprobar
Requires-Dist: poetry
Requires-Dist: numpy
Requires-Dist: pandas
Requires-Dist: matplotlib
Requires-Dist: opencv-python
Requires-Dist: streamlit
Requires-Dist: plotly
